base_agent/__init__.py
base_agent-2025.5.180920.dist-info/licenses/LICENSE
tests/__init__.py
tests/test_base_agent.py
base_agent-2025.5.180920.dist-info/METADATA
base_agent-2025.5.180920.dist-info/WHEEL
base_agent-2025.5.180920.dist-info/top_level.txt
base_agent-2025.5.180920.dist-info/RECORD
